exceltools/__init__.py
exceltools/excelread.py
exceltools/excelwrite.py
exceltools-0.1.9.dist-info/METADATA
exceltools-0.1.9.dist-info/WHEEL
exceltools-0.1.9.dist-info/top_level.txt
exceltools-0.1.9.dist-info/RECORD
