Metadata-Version: 2.1
Name: exceltools
Version: 0.1.9
Summary: report in excel.
Home-page: UNKNOWN
Author: Danian Hu
Author-email: hudanian@gmail.com
License: UNKNOWN
Platform: UNKNOWN
Requires-Dist: xlrd
Requires-Dist: xlsxwriter
